docling_ocr_onnxtr/__init__.py
docling_ocr_onnxtr/onnxtr_model.py
docling_ocr_onnxtr/options.py
docling_ocr_onnxtr/plugin.py
docling_ocr_onnxtr/py.typed
docling_ocr_onnxtr/version.py
docling_ocr_onnxtr-0.2.0.dist-info/licenses/LICENSE
docling_ocr_onnxtr-0.2.0.dist-info/METADATA
docling_ocr_onnxtr-0.2.0.dist-info/WHEEL
docling_ocr_onnxtr-0.2.0.dist-info/entry_points.txt
docling_ocr_onnxtr-0.2.0.dist-info/top_level.txt
docling_ocr_onnxtr-0.2.0.dist-info/zip-safe
docling_ocr_onnxtr-0.2.0.dist-info/RECORD
