Metadata-Version: 2.4
Name: docling-ocr-onnxtr
Version: 0.2.0
Summary: Onnx Text Recognition (OnnxTR) OCR plugin for docling
Author-email: Felix Dittrich <felixdittrich92@gmail.com>
Maintainer: Felix Dittrich
License:                                  Apache License
Project-URL: repository, https://github.com/felixdittrich92/docling-OCR-OnnxTR/OnnxTR
Project-URL: tracker, https://github.com/felixdittrich92/docling-OCR-OnnxTR/issues
Project-URL: changelog, https://github.com/felixdittrich92/docling-OCR-OnnxTR/releases
Keywords: OCR,deep learning,computer vision,onnx,text detection,text recognition,docTR,document analysis,document processing,document AI,docling,plugin
Classifier: Development Status :: 4 - Beta
Classifier: Intended Audience :: Developers
Classifier: Intended Audience :: Education
Classifier: Intended Audience :: Science/Research
Classifier: License :: OSI Approved :: Apache Software License
Classifier: Natural Language :: English
Classifier: Operating System :: OS Independent
Classifier: Programming Language :: Python :: 3
Classifier: Programming Language :: Python :: 3.10
Classifier: Programming Language :: Python :: 3.11
Classifier: Programming Language :: Python :: 3.12
Classifier: Topic :: Scientific/Engineering :: Artificial Intelligence
Requires-Python: <4,>=3.10.0
License-File: LICENSE
Requires-Dist: pydantic
Requires-Dist: docling<3.0.0,>=2.27.0
Provides-Extra: cpu
Requires-Dist: onnxtr[cpu]<1.0.0,>=0.6.2; extra == "cpu"
Provides-Extra: gpu
Requires-Dist: onnxtr[gpu]<1.0.0,>=0.6.2; extra == "gpu"
Provides-Extra: openvino
Requires-Dist: onnxtr[openvino]<1.0.0,>=0.6.2; extra == "openvino"
Provides-Extra: cpu-headless
Requires-Dist: onnxtr[cpu-headless]<1.0.0,>=0.6.2; extra == "cpu-headless"
Provides-Extra: gpu-headless
Requires-Dist: onnxtr[gpu-headless]<1.0.0,>=0.6.2; extra == "gpu-headless"
Provides-Extra: openvino-headless
Requires-Dist: onnxtr[openvino-headless]<1.0.0,>=0.6.2; extra == "openvino-headless"
Provides-Extra: testing
Requires-Dist: pytest>=5.3.2; extra == "testing"
Requires-Dist: coverage[toml]>=4.5.4; extra == "testing"
Requires-Dist: requests>=2.20.0; extra == "testing"
Provides-Extra: quality
Requires-Dist: ruff>=0.1.5; extra == "quality"
Requires-Dist: mypy>=0.812; extra == "quality"
Requires-Dist: pre-commit>=2.17.0; extra == "quality"
Provides-Extra: dev
Requires-Dist: onnxtr[gpu]; extra == "dev"
Requires-Dist: pytest>=5.3.2; extra == "dev"
Requires-Dist: coverage[toml]>=4.5.4; extra == "dev"
Requires-Dist: requests>=2.20.0; extra == "dev"
Requires-Dist: ruff>=0.1.5; extra == "dev"
Requires-Dist: mypy>=0.812; extra == "dev"
Requires-Dist: pre-commit>=2.17.0; extra == "dev"
Dynamic: license-file
